<?xml version="1.0" encoding="utf-8"?>
<association id="d1f697e4-85b4-43e4-8a43-aa7468d3d1a5">
  <sourceEnd id="c9675f3d-7547-46e9-abdb-28f77d9f67a8" type="Message Publish Assocation Source End" typeId="282eea12-2b98-4f0f-a28c-50c05b953c8e">
    <display>publisher: Webinar.Demo.Ordering</display>
    <order>0</order>
    <typeReference id="567396c5-e961-4efd-ba74-737b26edc7d1">
      <typeId>9e750045-6b86-4bd1-ab92-5cdad10bb854</typeId>
      <isNavigable>false</isNavigable>
      <isNullable>false</isNullable>
      <isCollection>false</isCollection>
      <isRequired>true</isRequired>
      <typePackageName>Webinar.Demo.Ordering.Eventing</typePackageName>
      <typePackageId>4fb13e32-ef0f-4708-821b-961eee9521b4</typePackageId>
      <stereotypes />
      <genericTypeParameters />
    </typeReference>
    <stereotypes />
    <metadata />
    <childElements />
  </sourceEnd>
  <targetEnd id="d1f697e4-85b4-43e4-8a43-aa7468d3d1a5" type="Message Publish Assocation Target End" typeId="6be8d569-70b9-4451-bd1b-7b654499503e">
    <display>publish: ProductCreatedEvent</display>
    <order>4</order>
    <typeReference id="2bc7d2de-6142-4b47-848a-4c2b7bd7e967">
      <typeId>fc1b3f5f-758b-4d83-8ec3-60c6e3543e73</typeId>
      <isNavigable>true</isNavigable>
      <isNullable>false</isNullable>
      <isCollection>false</isCollection>
      <isRequired>true</isRequired>
      <typePackageName>Webinar.Demo.Ordering.Eventing.Messages</typePackageName>
      <typePackageId>acbc6ad0-90f2-49f5-9f1e-b6fcf2ce629a</typePackageId>
      <stereotypes />
      <genericTypeParameters />
    </typeReference>
    <stereotypes />
    <metadata />
    <childElements />
  </targetEnd>
  <associationType>Message Publish Assocation</associationType>
  <associationTypeId>022d4c90-e1b6-4747-a15f-640c19503a8f</associationTypeId>
  <stereotypes />
</association>